MANIFEST.in
README.md
build.py
pyproject.toml
requirements-dev.txt
requirements.txt
setup.py
live_api/base.py
live_api/endpoints/__init__.py
live_api/endpoints/data.py
live_api/endpoints/engine.py
live_api/endpoints/exceptions.py
live_api/endpoints/process.py
live_api/service/__init__.py
live_api/service/rest.py
live_api/service/sockets.py
live_api/source/assets/icon/icon.ico
live_api/source/assets/icon/icon.png
live_fast_api.egg-info/PKG-INFO
live_fast_api.egg-info/SOURCES.txt
live_fast_api.egg-info/dependency_links.txt
live_fast_api.egg-info/requires.txt
live_fast_api.egg-info/top_level.txt