Metadata-Version: 2.1
Name: live-fast-api
Version: 1.0.1
Summary: A framework for developing responsive, live and dynamic REST APIs with python.
Home-page: https://github.com/Shahaf-F-S/live-api
Author: Shahaf Frank-Shapir
Author-email: shahaffrs@gmail.com
License: MIT
Platform: UNKNOWN
Classifier: Intended Audience :: Developers
Classifier: License :: OSI Approved :: MIT License
Classifier: Programming Language :: Python
Classifier: Programming Language :: Python :: 3
Classifier: Programming Language :: Python :: 3.8
Classifier: Programming Language :: Python :: 3.9
Classifier: Programming Language :: Python :: 3.10
Classifier: Programming Language :: Python :: 3.11
Classifier: Operating System :: OS Independent
Provides-Extra: dev
